configs/image_clf_configs.py
configs/image_det_configs.py
configs/image_seg_configs.py
configs/text_json_configs.py
datum/create_tfrecord.py
datum/version.py
datum/cache/__init__.py
datum/cache/bucket.py
datum/configs/__init__.py
datum/configs/config_base.py
datum/configs/default_configs.py
datum/configs/tfr_configs.py
datum/encoder/__init__.py
datum/encoder/encoder.py
datum/encoder/tokenizer.py
datum/export/__init__.py
datum/export/export.py
datum/generator/__init__.py
datum/generator/generator.py
datum/generator/image.py
datum/generator/text.py
datum/problem/problem.py
datum/problem/types.py
datum/reader/__init__.py
datum/reader/dataset.py
datum/reader/loader.py
datum/reader/parser.py
datum/reader/tfrecord_reader.py
datum/serializer/__init__.py
datum/serializer/serializer.py
datum/utils/__init__.py
datum/utils/binary_utils.py
datum/utils/common_utils.py
datum/utils/hashing.py
datum/utils/reader_utils.py
datum/utils/shard_utils.py
datum/utils/tqdm_utils.py
datum/utils/types_utils.py
datum/writer/__init__.py
datum/writer/tfrecord_writer.py
datum-1.13.0.dist-info/AUTHORS
datum-1.13.0.dist-info/LICENSE
datum-1.13.0.dist-info/METADATA
datum-1.13.0.dist-info/WHEEL
datum-1.13.0.dist-info/top_level.txt
datum-1.13.0.dist-info/RECORD
