Metadata-Version: 2.2
Name: datum
Version: 1.13.0
Summary: Datum provides APIs to create tfrecord daatsets and read tfrecord as tf.data.Datasets
Home-page: https://github.com/openagi/datum
Download-URL: https://github.com/openagi/datum/tags
Author: OpenAGI
Author-email: maintainer@openagi.io
License: Apache 2.0
Keywords: datum tensorflow tf.data datasets tfrecord
Classifier: Intended Audience :: Developers
Classifier: Intended Audience :: Science/Research
Classifier: License :: OSI Approved :: Apache Software License
Requires-Python: >=3.7
License-File: LICENSE
License-File: AUTHORS
Requires-Dist: tensorflow<2.22
Requires-Dist: pillow>=9.2.0
Requires-Dist: absl-py>=0.10
Requires-Dist: tqdm>=4.39.0
Requires-Dist: wrapt>=1.14.1
Requires-Dist: numpy<=1.27.0
Dynamic: author
Dynamic: author-email
Dynamic: classifier
Dynamic: description
Dynamic: download-url
Dynamic: home-page
Dynamic: keywords
Dynamic: license
Dynamic: requires-dist
Dynamic: requires-python
Dynamic: summary
